efmcalculator2/StateMachine.py
efmcalculator2/__init__.py
efmcalculator2/_version.py
efmcalculator2/cli.py
efmcalculator2/constants.py
efmcalculator2/utilities.py
efmcalculator2/data/__init__.py
efmcalculator2/data/gam_df.csv
efmcalculator2/ingest/EFMSequence.py
efmcalculator2/ingest/__init__.py
efmcalculator2/ingest/bad_state_mitigation.py
efmcalculator2/ingest/parse_inputs.py
efmcalculator2/pipeline/__init__.py
efmcalculator2/pipeline/classify_srs_rmd.py
efmcalculator2/pipeline/classify_ssr.py
efmcalculator2/pipeline/detection_strats.py
efmcalculator2/pipeline/features.py
efmcalculator2/pipeline/filtering.py
efmcalculator2/pipeline/mutation_rates.py
efmcalculator2/pipeline/post_process.py
efmcalculator2/pipeline/primary_pipeline.py
efmcalculator2/pipeline/subsequence_curation.py
efmcalculator2/webapp/SequenceState.py
efmcalculator2/webapp/__init__.py
efmcalculator2/webapp/bokeh_plot.py
efmcalculator2/webapp/bootstrap_streamlit.py
efmcalculator2/webapp/vis_utils.py
efmcalculator2/webapp/webapp.py
efmcalculator2/webapp/assets/favicon.ico
efmcalculator2/webapp/assets/html_template.html
efmcalculator2/webapp/assets/stylesheet.css
efmcalculator2/webapp/assets/tombstone.ai
efmcalculator2/webapp/assets/tombstone.svg
efmcalculator2-0.0.post1.dist-info/licenses/LICENSE.txt
efmcalculator2-0.0.post1.dist-info/METADATA
efmcalculator2-0.0.post1.dist-info/WHEEL
efmcalculator2-0.0.post1.dist-info/entry_points.txt
efmcalculator2-0.0.post1.dist-info/top_level.txt
efmcalculator2-0.0.post1.dist-info/RECORD
